astrovishal/Perceptron.py
astrovishal/__init__.py
astrovishalPerceptronPkg_astrovishalthakur-0.0.4.dist-info/LICENSE
astrovishalPerceptronPkg_astrovishalthakur-0.0.4.dist-info/METADATA
astrovishalPerceptronPkg_astrovishalthakur-0.0.4.dist-info/WHEEL
astrovishalPerceptronPkg_astrovishalthakur-0.0.4.dist-info/top_level.txt
astrovishalPerceptronPkg_astrovishalthakur-0.0.4.dist-info/RECORD
