Metadata-Version: 2.1
Name: astrovishalPerceptronPkg-astrovishalthakur
Version: 0.0.4
Summary: A small package for perceptron
Home-page: https://github.com/astrovishalthakur/astrovishalPerceptPkg
Author: astrovishalthakur
Author-email: astrovishalthakur@gmail.com
Project-URL: Bug Tracker, https://github.com/astrovishalthakur/astrovishalPerceptPkg/issues
Classifier: Programming Language :: Python :: 3
Classifier: License :: OSI Approved :: MIT License
Classifier: Operating System :: OS Independent
Requires-Python: >=3.6
License-File: LICENSE
